[
  {
    "name": "505",
    "img":"/images/vinos/vino1.jpg",
    "desc": "Lorem ipsum dolor sit amet, consectetur adipiscing elit. Duis venenatis pretium risus, nec pulvinar mi pulvinar ac."
  },
  {
    "name": "506",
    "img":"/images/vinos/vino2.jpg",
    "desc": "Lorem ipsum dolor sit amet, consectetur adipiscing elit. Duis venenatis pretium risus, nec pulvinar mi pulvinar ac."
  },
  {
    "name": "507",
    "img":"/images/vinos/vino3.jpg",
    "desc": "Lorem ipsum dolor sit amet, consectetur adipiscing elit. Duis venenatis pretium risus, nec pulvinar mi pulvinar ac."
  },
  {
    "name": "508",
    "img":"/images/vinos/vino4.jpg",
    "desc": "Lorem ipsum dolor sit amet, consectetur adipiscing elit. Duis venenatis pretium risus, nec pulvinar mi pulvinar ac."
  },
  {
    "name": "509",
    "img":"/images/vinos/vino5.jpg",
    "desc": "Lorem ipsum dolor sit amet, consectetur adipiscing elit. Duis venenatis pretium risus, nec pulvinar mi pulvinar ac."
  },
  {
    "name": "500",
    "img":"/images/vinos/vino6.jpg",
    "desc": "Lorem ipsum dolor sit amet, consectetur adipiscing elit. Duis venenatis pretium risus, nec pulvinar mi pulvinar ac."
  }
]